CHANGELOG.md
LICENSE
MANIFEST.in
README.md
pytest.ini
setup.cfg
setup.py
versioneer.py
pynanocurrency.egg-info/PKG-INFO
pynanocurrency.egg-info/SOURCES.txt
pynanocurrency.egg-info/dependency_links.txt
pynanocurrency.egg-info/requires.txt
pynanocurrency.egg-info/top_level.txt
src/nanocurrency/__init__.py
src/nanocurrency/_version.py
src/nanocurrency/accounts.py
src/nanocurrency/blocks.py
src/nanocurrency/exceptions.py
src/nanocurrency/units.py
src/nanocurrency/util.py
src/nanocurrency/work.py
src/nanocurrency-work-module/work.c
src/nanocurrency-work-module/ref/blake2-impl.h
src/nanocurrency-work-module/ref/blake2.h
src/nanocurrency-work-module/ref/blake2b-ref.c
src/nanocurrency-work-module/ref/blake2bp-ref.c
src/nanocurrency-work-module/ref/blake2s-ref.c
src/nanocurrency-work-module/ref/blake2sp-ref.c
src/nanocurrency-work-module/ref/blake2xb-ref.c
src/nanocurrency-work-module/ref/blake2xs-ref.c
src/nanocurrency-work-module/ref/makefile
src/nanocurrency-work-module/sse/blake2-config.h
src/nanocurrency-work-module/sse/blake2-impl.h
src/nanocurrency-work-module/sse/blake2.h
src/nanocurrency-work-module/sse/blake2b-load-sse2.h
src/nanocurrency-work-module/sse/blake2b-load-sse41.h
src/nanocurrency-work-module/sse/blake2b-round.h
src/nanocurrency-work-module/sse/blake2b.c
src/nanocurrency-work-module/sse/blake2bp.c
src/nanocurrency-work-module/sse/blake2s-load-sse2.h
src/nanocurrency-work-module/sse/blake2s-load-sse41.h
src/nanocurrency-work-module/sse/blake2s-load-xop.h
src/nanocurrency-work-module/sse/blake2s-round.h
src/nanocurrency-work-module/sse/blake2s.c
src/nanocurrency-work-module/sse/blake2sp.c
src/nanocurrency-work-module/sse/blake2xb.c
src/nanocurrency-work-module/sse/blake2xs.c
src/nanocurrency-work-module/sse/makefile
tests/__init__.py
tests/conftest.py
tests/data.py
tests/performance_test.py
tests/test_accounts.py
tests/test_blocks.py
tests/test_units.py
tests/test_work.py