Metadata-Version: 1.2
Name: pynanocurrency
Version: 0.1.post1
Summary: Python library for working with the NANO cryptocurrency protocol
Home-page: https://github.com/Matoking/pynanocurrency
Author: Janne Pulkkinen
Author-email: jannepulk@gmail.com
License: CC0
Platform: UNKNOWN
Classifier: Programming Language :: Python
Classifier: Programming Language :: Python :: 3
Classifier: Programming Language :: Python :: 3.6
Classifier: Programming Language :: Python :: 3.7
Classifier: Programming Language :: Python :: Implementation :: CPython
Classifier: Operating System :: POSIX :: Linux
Classifier: Topic :: Office/Business :: Financial
Requires-Python: >=3.6.0
